{
	"partitions" : [
		{
			"name" : "Top",
			"pins" : [
				{
					"name" : "I2C_SCLK",
					"strict" : false
				},
				{
					"name" : "G_SENSOR_CS_N",
					"strict" : false
				},
				{
					"name" : "LEDS[0]",
					"strict" : false
				},
				{
					"name" : "LEDS[1]",
					"strict" : false
				},
				{
					"name" : "LEDS[2]",
					"strict" : false
				},
				{
					"name" : "LEDS[3]",
					"strict" : false
				},
				{
					"name" : "LEDS[4]",
					"strict" : false
				},
				{
					"name" : "LEDS[5]",
					"strict" : false
				},
				{
					"name" : "LEDS[6]",
					"strict" : false
				},
				{
					"name" : "LEDS[7]",
					"strict" : false
				},
				{
					"name" : "LEDS_OUT[0]",
					"strict" : false
				},
				{
					"name" : "LEDS_OUT[1]",
					"strict" : false
				},
				{
					"name" : "LEDS_OUT[2]",
					"strict" : false
				},
				{
					"name" : "LEDS_OUT[3]",
					"strict" : false
				},
				{
					"name" : "LEDS_OUT[4]",
					"strict" : false
				},
				{
					"name" : "LEDS_OUT[5]",
					"strict" : false
				},
				{
					"name" : "LEDS_OUT[6]",
					"strict" : false
				},
				{
					"name" : "LEDS_OUT[7]",
					"strict" : false
				},
				{
					"name" : "LEDS_OUT[8]",
					"strict" : false
				},
				{
					"name" : "LEDS_OUT[9]",
					"strict" : false
				},
				{
					"name" : "LEDS_OUT[10]",
					"strict" : false
				},
				{
					"name" : "LEDS_OUT[11]",
					"strict" : false
				},
				{
					"name" : "LEDS_OUT[12]",
					"strict" : false
				},
				{
					"name" : "LEDS_OUT[13]",
					"strict" : false
				},
				{
					"name" : "LEDS_OUT[14]",
					"strict" : false
				},
				{
					"name" : "LEDS_OUT[15]",
					"strict" : false
				},
				{
					"name" : "I2C_SDAT",
					"strict" : false
				},
				{
					"name" : "reset_n",
					"strict" : false
				},
				{
					"name" : "CLK",
					"strict" : false
				}
			]
		}
	]
}